donjuan/__init__.py
donjuan/cell.py
donjuan/doorspace.py
donjuan/dungeon.py
donjuan/face.py
donjuan/grid.py
donjuan-0.0.2.dist-info/LICENSE
donjuan-0.0.2.dist-info/METADATA
donjuan-0.0.2.dist-info/WHEEL
donjuan-0.0.2.dist-info/top_level.txt
donjuan-0.0.2.dist-info/RECORD
