Metadata-Version: 2.1
Name: donjuan
Version: 0.0.2
Summary: Package for generating dungeons.
Home-page: https://github.com/tmcclintock/PyDonJuan
Author: Tom McClintock
Author-email: thmsmcclintock@gmail.com
License: UNKNOWN
Platform: UNKNOWN
Classifier: Programming Language :: Python :: 3
Classifier: Operating System :: OS Independent
Requires-Python: >=3.6
